zcscommonlib/__init__.py
zcscommonlib/functions.py
zcscommonlib/zcsmath.py
zcscommonlib-0.3.6.dist-info/LICENSE
zcscommonlib-0.3.6.dist-info/METADATA
zcscommonlib-0.3.6.dist-info/WHEEL
zcscommonlib-0.3.6.dist-info/top_level.txt
zcscommonlib-0.3.6.dist-info/RECORD
