Metadata-Version: 2.1
Name: zcscommonlib
Version: 0.3.6
Summary: A Common Library For Use In Computer Science Projects
Home-page: https://commonlib.zandercraft.ca
Author: Zandercraft
License: MPL 2.0
Download-URL: https://github.com/Zandercraft/ZCSCommonLibrary/archive/0.3.5.tar.gz
Platform: UNKNOWN
Classifier: Development Status :: 3 - Alpha
Classifier: Intended Audience :: Developers
Classifier: Topic :: Software Development :: Build Tools
Classifier: Programming Language :: Python :: 3.6
Classifier: Programming Language :: Python :: 3.7
Classifier: Programming Language :: Python :: 3.8
